abouttag/__init__.py
abouttag/about.py
abouttag/amazon.py
abouttag/books.py
abouttag/database.py
abouttag/film.py
abouttag/fluiddb.py
abouttag/generic.py
abouttag/location.py
abouttag/music.py
abouttag/nacolike.py
abouttag/objects.py
abouttag/test.py
abouttag/uri.py
abouttag-1.3.1.dist-info/LICENSE
abouttag-1.3.1.dist-info/METADATA
abouttag-1.3.1.dist-info/WHEEL
abouttag-1.3.1.dist-info/top_level.txt
abouttag-1.3.1.dist-info/RECORD
