Metadata-Version: 2.1
Name: abouttag
Version: 1.3.1
Summary: Normalizes about tags for Fluidinfo
Home-page: http://github.com/njr0/abouttag/
Author: Nicholas J. Radcliffe
Author-email: njr@StochasticSolutions.com
License: UNKNOWN
Download-URL: https://github.com/njr0/abouttag
Keywords: fluidinfo,about,tag,normalization,canonicalization,standardarization
Platform: UNKNOWN
Classifier: Programming Language :: Python
Classifier: Programming Language :: Python :: 3
Classifier: Development Status :: 5 - Production/Stable
Classifier: License :: OSI Approved :: MIT License
Classifier: Environment :: Other Environment
Classifier: Intended Audience :: Developers
Classifier: Topic :: Software Development :: Libraries :: Python Modules
Classifier: Topic :: Internet
License-File: LICENSE
Requires-Dist: urlnorm (>=1.1.2)
